autocar3/Util.py
autocar3/__init__.py
autocar3/config.py
autocar3/driving.py
autocar3/sensors.py
autocar3/LiDAR/__init__.py
autocar3/LiDAR/lidar2d.py
autocar3/LiDAR/lidar2d_imp.py
autocar3/LiDAR/rplidar.py
autocar3/options/Analog.py
autocar3/options/CAN.py
autocar3/options/PGCA.py
autocar3/options/RGB.py
autocar3/options/Switch.py
autocar3/options/TPHG.py
autocar3/options/Thermopile.py
autocar3/options/ToF.py
autocar3/options/__init__.py
pop_autocar3-1.0.0.dist-info/METADATA
pop_autocar3-1.0.0.dist-info/WHEEL
pop_autocar3-1.0.0.dist-info/top_level.txt
pop_autocar3-1.0.0.dist-info/RECORD
