Metadata-Version: 2.1
Name: pop-autocar3
Version: 1.0.0
Summary: AIoT AutoCar3 library for pop
Home-page: UNKNOWN
Author: hanback-lab
Author-email: lab@hanback.co.kr
License: UNKNOWN
Platform: UNKNOWN
Classifier: Programming Language :: Python :: 3
Classifier: License :: OSI Approved :: MIT License
Classifier: Operating System :: OS Independent
Requires-Python: >=3.6
Requires-Dist: pop-genlib
Requires-Dist: traitlets
Requires-Dist: pyaudio
Requires-Dist: librosa
Requires-Dist: ipywidgets
Requires-Dist: opencv-python
